{"_id":"de9e5c10-58e7-11e8-bebb-13146c4ef23d","name":"AzuoyTutle","email":"c3545bb60cf7b9c9c9239f22d98f1a28","body":"https://aussiecasinomate.com/# - rich casino https://aussiecasinomate.com/# - treasury casino https://aussiecasinomate.com/# - crown casino perth \r\n<a href=\"https://aussiecasinomate.com/#\">tangiers casino login</a> <a href=\"https://aussiecasinomate.com/#\">crown casino perth</a> <a href=\"https://aussiecasinomate.com/#\">mongoose casino</a> \r\n<a href=\" https://aussiecasinomate.com/# \">doubledown casino</a>","date":"2018-05-16T09:02:33.384Z"}